{
  "meta": {
    "games_per_pair": 500,
    "seed": 42,
    "competitors": [
      "Expert",
      "Distill14_v2"
    ],
    "elapsed_min": 1.37,
    "total_games": 500
  },
  "pairs": [
    {
      "a": "Expert",
      "b": "Distill14_v2",
      "n_games": 500,
      "a_wins": 127,
      "b_wins": 373,
      "draws": 0,
      "a_wr_pct": 25.4,
      "b_wr_pct": 74.6,
      "avg_length": 162.12,
      "seat_a_p0": [
        55,
        250
      ],
      "seat_a_p2": [
        72,
        250
      ],
      "pair": [
        "Expert",
        "Distill14_v2"
      ]
    }
  ]
}